contact_space-0.1.9.dist-info/licenses/LICENSE
contactspace/__init__.py
contactspace/checks.py
contactspace/contactspace.py
contactspace/exceptions.py
examples/auth_example.py
contact_space-0.1.9.dist-info/METADATA
contact_space-0.1.9.dist-info/WHEEL
contact_space-0.1.9.dist-info/top_level.txt
contact_space-0.1.9.dist-info/RECORD
