Metadata-Version: 2.4
Name: contact_space
Version: 0.1.9
Summary: SDK to interact with the ContactSpace REST API
Author-email: George Burns <mrgeorgegburns@gmail.com>
License: MIT
Classifier: Programming Language :: Python :: 3
Classifier: License :: OSI Approved :: MIT License
Classifier: Operating System :: OS Independent
Requires-Python: >=3.7
License-File: LICENSE
Requires-Dist: requests
Requires-Dist: pandas
Requires-Dist: python-dateutil
Dynamic: license-file
